{
  "schemaVersion": 1,
  "id": "gem-dolphin",
  "version": "${version}",
  "name": "gem-dolphin",
  "description": "",
  "authors": [],
  "contact": {
    "repo": "https://github.com/gavinsmod/gem-dolphin"
  },
  "license": "MIT",
  "icon": "assets/gem-dolphin/icon.png",
  "environment": "client",
  "entrypoints": {
    "main": [
      "com.peasenet.mod.DolphinMod"
    ]
  },
  "depends": {
    "fabricloader": ">=${loader_version}",
    "gemclient-core": "1.0.3",
    "fabric": "*",
    "minecraft": "${minecraft_version}"
  }
}
